cutiepynb/.DS_Store
cutiepynb/__init__.py
cutiepynb/core.py
cutiepynb/styles.py
cutiepynb/utils.py
cutiepynb-1.0.0.dist-info/LICENSE
cutiepynb-1.0.0.dist-info/METADATA
cutiepynb-1.0.0.dist-info/WHEEL
cutiepynb-1.0.0.dist-info/entry_points.txt
cutiepynb-1.0.0.dist-info/top_level.txt
cutiepynb-1.0.0.dist-info/RECORD
