Metadata-Version: 2.1
Name: cutiepynb
Version: 1.0.0
Summary: Make your Jupyter notebooks pretty with custom colors and a table of contents.
Author-email: Elisa Márquez-Zavala <emarquez@lcg.unam.mx>
License: MIT License
Project-URL: Homepage, https://github.com/emarquezz/cutiepynb
Keywords: cutiepynb
Classifier: Intended Audience :: Developers
Classifier: License :: OSI Approved :: MIT License
Classifier: Natural Language :: English
Classifier: Programming Language :: Python :: 3.8
Classifier: Programming Language :: Python :: 3.9
Classifier: Programming Language :: Python :: 3.10
Classifier: Programming Language :: Python :: 3.11
Classifier: Programming Language :: Python :: 3.12
Requires-Python: >=3.8
License-File: LICENSE
Requires-Dist: numpy
Provides-Extra: all
Requires-Dist: cutiepynb[extra] ; extra == 'all'
Provides-Extra: extra
Requires-Dist: pandas ; extra == 'extra'
